wpdm/__init__.py
wpdm/models.py
wpdm/utils.py
wpdm3333-0.1.0.dist-info/LICENSE
wpdm3333-0.1.0.dist-info/METADATA
wpdm3333-0.1.0.dist-info/WHEEL
wpdm3333-0.1.0.dist-info/top_level.txt
wpdm3333-0.1.0.dist-info/RECORD
